pineappl-1.3.0.dist-info/METADATA
pineappl-1.3.0.dist-info/WHEEL
pineappl/__init__.py
pineappl/pineappl.cp312-win_amd64.pyd
pineappl-1.3.0.dist-info/RECORD
