Metadata-Version: 2.4
Name: pineappl
Version: 1.3.0
Classifier: Development Status :: 4 - Beta
Classifier: Intended Audience :: Science/Research
Classifier: License :: OSI Approved :: GNU General Public License v3 or later (GPLv3+)
Classifier: Natural Language :: English
Classifier: Operating System :: MacOS
Classifier: Operating System :: Microsoft :: Windows
Classifier: Operating System :: POSIX
Classifier: Programming Language :: Python :: 3 :: Only
Classifier: Programming Language :: Rust
Classifier: Topic :: Scientific/Engineering :: Physics
Requires-Dist: numpy>=1.16.0
Requires-Dist: pineappl-cli ; extra == 'cli'
Requires-Dist: sphinx>=7.0.0 ; extra == 'docs'
Requires-Dist: sphinx-rtd-theme>=1.2.2 ; extra == 'docs'
Requires-Dist: nbsphinx>=0.8.8 ; extra == 'docs'
Requires-Dist: ipykernel>=6.13.0 ; extra == 'docs'
Requires-Dist: polars>=1.8.0 ; extra == 'docs'
Requires-Dist: pytest ; extra == 'test'
Requires-Dist: pytest-cov ; extra == 'test'
Provides-Extra: cli
Provides-Extra: docs
Provides-Extra: test
Requires-Python: >=3.7
Project-URL: homepage, https://nnpdf.github.io/pineappl/
Project-URL: documentation, https://pineappl.readthedocs.io/
Project-URL: changelog, https://nnpdf.github.io/pineappl/CHANGELOG.html
